{
  "info": {
    "name": "Post Analytics API",
    "_postman_id": "2f209f44-4f5e-4a9b-8bc0-e7c8f95e3c28",
    "description": "Postman collection for the Post Analytics backend assessment project.",
    "schema": "https://schema.getpostman.com/json/collection/v2.1.0/collection.json"
  },
  "variable": [
    {
      "key": "baseUrl",
      "value": "http://localhost:3000"
    },
    {
      "key": "jwtToken",
      "value": ""
    },
    {
      "key": "articleId",
      "value": ""
    }
  ],
  "item": [
    {
      "name": "Health",
      "item": [
        {
          "name": "GET /health",
          "request": {
            "method": "GET",
            "header": [],
            "url": {
              "raw": "{{baseUrl}}/health",
              "host": [
                "{{baseUrl}}"
              ],
              "path": [
                "health"
              ]
            }
          }
        }
      ]
    },
    {
      "name": "Auth",
      "item": [
        {
          "name": "POST /auth/register (author)",
          "request": {
            "method": "POST",
            "header": [
              {
                "key": "Content-Type",
                "value": "application/json"
              }
            ],
            "body": {
              "mode": "raw",
              "raw": "{\n  \"name\": \"Author Demo\",\n  \"email\": \"author.demo@example.com\",\n  \"password\": \"Strong@123\",\n  \"role\": \"author\"\n}"
            },
            "url": {
              "raw": "{{baseUrl}}/auth/register",
              "host": [
                "{{baseUrl}}"
              ],
              "path": [
                "auth",
                "register"
              ]
            }
          }
        },
        {
          "name": "POST /auth/register (reader)",
          "request": {
            "method": "POST",
            "header": [
              {
                "key": "Content-Type",
                "value": "application/json"
              }
            ],
            "body": {
              "mode": "raw",
              "raw": "{\n  \"name\": \"Reader Demo\",\n  \"email\": \"reader.demo@example.com\",\n  \"password\": \"Strong@123\",\n  \"role\": \"reader\"\n}"
            },
            "url": {
              "raw": "{{baseUrl}}/auth/register",
              "host": [
                "{{baseUrl}}"
              ],
              "path": [
                "auth",
                "register"
              ]
            }
          }
        },
        {
          "name": "POST /auth/login (author)",
          "event": [
            {
              "listen": "test",
              "script": {
                "exec": [
                  "const json = pm.response.json();",
                  "if (json && json.Object && json.Object.token) {",
                  "  pm.collectionVariables.set('jwtToken', json.Object.token);",
                  "}"
                ],
                "type": "text/javascript"
              }
            }
          ],
          "request": {
            "method": "POST",
            "header": [
              {
                "key": "Content-Type",
                "value": "application/json"
              }
            ],
            "body": {
              "mode": "raw",
              "raw": "{\n  \"email\": \"author.demo@example.com\",\n  \"password\": \"Strong@123\"\n}"
            },
            "url": {
              "raw": "{{baseUrl}}/auth/login",
              "host": [
                "{{baseUrl}}"
              ],
              "path": [
                "auth",
                "login"
              ]
            }
          }
        },
        {
          "name": "POST /auth/login (reader)",
          "request": {
            "method": "POST",
            "header": [
              {
                "key": "Content-Type",
                "value": "application/json"
              }
            ],
            "body": {
              "mode": "raw",
              "raw": "{\n  \"email\": \"reader.demo@example.com\",\n  \"password\": \"Strong@123\"\n}"
            },
            "url": {
              "raw": "{{baseUrl}}/auth/login",
              "host": [
                "{{baseUrl}}"
              ],
              "path": [
                "auth",
                "login"
              ]
            }
          }
        }
      ]
    },
    {
      "name": "Articles",
      "item": [
        {
          "name": "GET /articles",
          "request": {
            "method": "GET",
            "header": [],
            "url": {
              "raw": "{{baseUrl}}/articles?page=1&pageSize=10",
              "host": [
                "{{baseUrl}}"
              ],
              "path": [
                "articles"
              ],
              "query": [
                {
                  "key": "page",
                  "value": "1"
                },
                {
                  "key": "pageSize",
                  "value": "10"
                }
              ]
            }
          }
        },
        {
          "name": "POST /articles (author only)",
          "event": [
            {
              "listen": "test",
              "script": {
                "exec": [
                  "const json = pm.response.json();",
                  "if (json && json.Object && json.Object.id) {",
                  "  pm.collectionVariables.set('articleId', json.Object.id);",
                  "}"
                ],
                "type": "text/javascript"
              }
            }
          ],
          "request": {
            "method": "POST",
            "header": [
              {
                "key": "Authorization",
                "value": "Bearer {{jwtToken}}"
              },
              {
                "key": "Content-Type",
                "value": "application/json"
              }
            ],
            "body": {
              "mode": "raw",
              "raw": "{\n  \"title\": \"Backend Assessment Implementation\",\n  \"content\": \"This article demonstrates a complete implementation with validation, RBAC, queue based analytics and testing coverage for key modules.\",\n  \"category\": \"Tech\",\n  \"status\": \"Published\"\n}"
            },
            "url": {
              "raw": "{{baseUrl}}/articles",
              "host": [
                "{{baseUrl}}"
              ],
              "path": [
                "articles"
              ]
            }
          }
        },
        {
          "name": "GET /articles/me (author only)",
          "request": {
            "method": "GET",
            "header": [
              {
                "key": "Authorization",
                "value": "Bearer {{jwtToken}}"
              }
            ],
            "url": {
              "raw": "{{baseUrl}}/articles/me?page=1&pageSize=10",
              "host": [
                "{{baseUrl}}"
              ],
              "path": [
                "articles",
                "me"
              ],
              "query": [
                {
                  "key": "page",
                  "value": "1"
                },
                {
                  "key": "pageSize",
                  "value": "10"
                }
              ]
            }
          }
        },
        {
          "name": "GET /articles/:id",
          "request": {
            "method": "GET",
            "header": [],
            "url": {
              "raw": "{{baseUrl}}/articles/{{articleId}}",
              "host": [
                "{{baseUrl}}"
              ],
              "path": [
                "articles",
                "{{articleId}}"
              ]
            }
          }
        },
        {
          "name": "PUT /articles/:id (author only)",
          "request": {
            "method": "PUT",
            "header": [
              {
                "key": "Authorization",
                "value": "Bearer {{jwtToken}}"
              },
              {
                "key": "Content-Type",
                "value": "application/json"
              }
            ],
            "body": {
              "mode": "raw",
              "raw": "{\n  \"title\": \"Backend Assessment Implementation - Updated\",\n  \"content\": \"This updated article body remains above the minimum content threshold and verifies update ownership checks in the API implementation.\",\n  \"category\": \"Tech\",\n  \"status\": \"Published\"\n}"
            },
            "url": {
              "raw": "{{baseUrl}}/articles/{{articleId}}",
              "host": [
                "{{baseUrl}}"
              ],
              "path": [
                "articles",
                "{{articleId}}"
              ]
            }
          }
        },
        {
          "name": "DELETE /articles/:id (author only)",
          "request": {
            "method": "DELETE",
            "header": [
              {
                "key": "Authorization",
                "value": "Bearer {{jwtToken}}"
              }
            ],
            "url": {
              "raw": "{{baseUrl}}/articles/{{articleId}}",
              "host": [
                "{{baseUrl}}"
              ],
              "path": [
                "articles",
                "{{articleId}}"
              ]
            }
          }
        }
      ]
    },
    {
      "name": "Analytics",
      "item": [
        {
          "name": "GET /author/dashboard (author only)",
          "request": {
            "method": "GET",
            "header": [
              {
                "key": "Authorization",
                "value": "Bearer {{jwtToken}}"
              }
            ],
            "url": {
              "raw": "{{baseUrl}}/author/dashboard?page=1&pageSize=10",
              "host": [
                "{{baseUrl}}"
              ],
              "path": [
                "author",
                "dashboard"
              ],
              "query": [
                {
                  "key": "page",
                  "value": "1"
                },
                {
                  "key": "pageSize",
                  "value": "10"
                }
              ]
            }
          }
        }
      ]
    }
  ]
}
